[
  {
    "key": "IMG20240327105047.jpg",
    "url": "/images/fotbarSMA/2023_2024/Kls_11_C/IMG20240327105047.jpg",
    "alt": "IMG20240327105047.jpg",
    "album_id": "2023_2024/Kls_11_C",
    "title": "IMG20240327105047.jpg",
    "id": "01f45c16-29e3-4296-9e00-4c8893d3a131",
    "filename": "IMG20240327105047.jpg",
    "width": 9248,
    "height": 6944
  },
  {
    "key": "IMG20240327105051.jpg",
    "url": "/images/fotbarSMA/2023_2024/Kls_11_C/IMG20240327105051.jpg",
    "alt": "IMG20240327105051.jpg",
    "album_id": "2023_2024/Kls_11_C",
    "title": "IMG20240327105051.jpg",
    "id": "f8e39476-b72e-4066-bb9a-46656c4ab82b",
    "filename": "IMG20240327105051.jpg",
    "width": 9248,
    "height": 6944
  },
  {
    "key": "IMG20240327105056.jpg",
    "url": "/images/fotbarSMA/2023_2024/Kls_11_C/IMG20240327105056.jpg",
    "alt": "IMG20240327105056.jpg",
    "album_id": "2023_2024/Kls_11_C",
    "title": "IMG20240327105056.jpg",
    "id": "c41a9340-e9de-4e31-96b8-3d67fc73537e",
    "filename": "IMG20240327105056.jpg",
    "width": 9248,
    "height": 6944
  },
  {
    "key": "IMG20240327105120.jpg",
    "url": "/images/fotbarSMA/2023_2024/Kls_11_C/IMG20240327105120.jpg",
    "alt": "IMG20240327105120.jpg",
    "album_id": "2023_2024/Kls_11_C",
    "title": "IMG20240327105120.jpg",
    "id": "ba0a4490-f66e-4598-b0b9-55bf58a57139",
    "filename": "IMG20240327105120.jpg",
    "width": 9248,
    "height": 6944
  },
  {
    "key": "IMG20240327105139.jpg",
    "url": "/images/fotbarSMA/2023_2024/Kls_11_C/IMG20240327105139.jpg",
    "alt": "IMG20240327105139.jpg",
    "album_id": "2023_2024/Kls_11_C",
    "title": "IMG20240327105139.jpg",
    "id": "db97bc6e-9da8-4a11-88ed-8cd7892064f5",
    "filename": "IMG20240327105139.jpg",
    "width": 9248,
    "height": 6944
  },
  {
    "key": "IMG20240327105303.jpg",
    "url": "/images/fotbarSMA/2023_2024/Kls_11_C/IMG20240327105303.jpg",
    "alt": "IMG20240327105303.jpg",
    "album_id": "2023_2024/Kls_11_C",
    "title": "IMG20240327105303.jpg",
    "id": "8e9f3f89-b1e6-49be-974c-ec07727a90e1",
    "filename": "IMG20240327105303.jpg",
    "width": 9248,
    "height": 6944
  },
  {
    "key": "IMG20240327105519.jpg",
    "url": "/images/fotbarSMA/2023_2024/Kls_11_C/IMG20240327105519.jpg",
    "alt": "IMG20240327105519.jpg",
    "album_id": "2023_2024/Kls_11_C",
    "title": "IMG20240327105519.jpg",
    "id": "e4f68b1b-2171-4cf2-a6db-31ed604173b6",
    "filename": "IMG20240327105519.jpg",
    "width": 9248,
    "height": 6944
  }
]